<?xml version="1.0" encoding="UTF-8"?>
<language key="dev">
 <category name="">
  <item name="btn_label_start"><![CDATA[INICIO]]></item>
  <item name="btn_label_loading"><![CDATA[CARGANDO]]></item>
  <item name="btn_label_loadstarsystem"><![CDATA[CARGANDO SISTEMA ESTELAR]]></item>
  <item name="hint_title_quests"><![CDATA[MISIONES]]></item>
  <item name="hint_title_quests_long"><![CDATA[Misiones]]></item>
  <item name="hint_subtitle_quests"><![CDATA[¿Buscas aventuras?]]></item>
  <item name="hint_description_quests"><![CDATA[¡Pues échale un vistazo a la <strong>página de misiones</strong>!  Haz clic en el menú principal sobre el <strong>botón de misiones</strong> y enfréntate a los desafíos que allí te esperan.]]></item>
  <item name="hint_title_group"><![CDATA[GRUPO]]></item>
  <item name="hint_title_group_long"><![CDATA[Grupo]]></item>
  <item name="hint_subtitle_group"><![CDATA[¿No quieres luchar solo?]]></item>
  <item name="hint_description_group"><![CDATA[Haz clic en el <strong>símbolo con las tres siluetas</strong> en el <strong>mapa espacial</strong>. Después podrás invitar a otros jugadores a un grupo o mirar si ya te han invitado a ti a alguno.]]></item>
  <item name="hint_title_equipping"><![CDATA[EQUIPAMIENTO]]></item>
  <item name="hint_title_equipping_long"><![CDATA[Equipamiento]]></item>
  <item name="hint_subtitle_equipping"><![CDATA[¿Necesitas nuevas armas?]]></item>
  <item name="hint_description_equipping"><![CDATA[En el menú principal, dentro del <strong>hangar</strong>, encontrarás armas, munición, potenciadores, VANTS y muchas otras cosas.<br><br>¡Equipa tu nave y mantente preparado para cualquier batalla!]]></item>
  <item name="hint_title_configurations"><![CDATA[CONFIGURACIONES]]></item>
  <item name="hint_title_configurations_long"><![CDATA[Configuraciones]]></item>
  <item name="hint_subtitle_configurations"><![CDATA[¿Buscas distintas tácticas?]]></item>
  <item name="hint_description_configurations"><![CDATA[¿Estás hasta la coronilla de tener que cambiar el equipamiento de tu nave continuamente? ¡Pues sácales provecho a las <strong>2 configuraciones distintas</strong> de la nave!<br><br>¡Equipa tu nave en el hangar con dos selecciones de objetos diferentes y cambia luego entre ellas pulsando la tecla <strong>C</strong>!]]></item>
  <item name="hint_title_premium"><![CDATA[VENTAJAS PREMIUM]]></item>
  <item name="hint_title_premium_long"><![CDATA[Ventajas Premium]]></item>
  <item name="hint_subtitle_premium"><![CDATA[¿Todos disfrutan de ventajas excepto tú?]]></item>
  <item name="hint_description_premium"><![CDATA[¡Pues no esperes más! Aprovecha ahora la oportunidad de conseguir <strong>reparaciones de nave gratuitas</strong> y muchas otras ventajas con los <strong>paquetes Premium</strong>.]]></item>
  <item name="hint_title_honor"><![CDATA[HONOR]]></item>
  <item name="hint_title_honor_long"><![CDATA[Honor]]></item>
  <item name="hint_subtitle_honor"><![CDATA[¡Defiende tu honor!]]></item>
  <item name="hint_description_honor"><![CDATA[Cuanto más honor consigas en el espacio, más rápido ascenderás de <strong>rango</strong> en tu empresa.<br>Realiza misiones, destruye todos los enemigos que puedas... ¡y conviértete en el piloto <strong>más honorable</strong> de la galaxia!]]></item>
  <item name="hint_title_uridium"><![CDATA[URIDIUM]]></item>
  <item name="hint_title_uridium_long"><![CDATA[Uridium]]></item>
  <item name="hint_subtitle_uridium"><![CDATA[¡El uridium lo es todo en el espacio!]]></item>
  <item name="hint_description_uridium"><![CDATA[Los alienígenas llevan muchas veces cargamentos de uridium... ¡destrúyelos! Y no te olvides de buscar también en las cajas bono.<br>¿No ha habido suerte? Entonces hazte con él directamente en el <strong>menú principal</strong> en la página <strong>"Uridium"</strong>.]]></item>
  <item name="hint_title_titanic"><![CDATA[La invasión de los icebergs]]></item>
  <item name="hint_title_titanic_long"><![CDATA[100 años del mito del Titanic]]></item>
  <item name="hint_subtitle_titanic"><![CDATA[¡Atención: se han localizado icebergs en DarkOrbit!]]></item>
  <item name="hint_description_titanic"><![CDATA[Hace 100 años, el Titanic, el buque más lujoso de su tiempo, chocó contra un iceberg y se hundió. Para conmemorar ese trágico accidente, <strong>desde el 14.04 hasta el 17.04</strong>, tendrá lugar nuestro acontecimiento sobre el hundimiento del Titanic.]]></item>
  <item name="hint_title_fullscreen"><![CDATA[PANTALLA COMPLETA]]></item>
  <item name="hint_title_fullscreen_long"><![CDATA[Pantalla completa]]></item>
  <item name="hint_subtitle_fullscreen"><![CDATA[Novedad: ¡DarkOrbit en pantalla completa!]]></item>
  <item name="hint_description_fullscreen"><![CDATA[A partir de ahora, puedes disfrutar de DarkOrbit también en <strong>pantalla completa</strong>.<br>Para ello, haz clic en el botón de pantalla completa del juego.]]></item>
  <item name="hint_title_fullscreenfpupdate"><![CDATA[PANTALLA COMPLETA]]></item>
  <item name="hint_title_fullscreenfpupdate_long"><![CDATA[Pantalla completa]]></item>
  <item name="hint_subtitle_fullscreenfpupdate"><![CDATA[¿Tienes ganas de disfrutar de DarkOrbit a lo grande?]]></item>
  <item name="hint_description_fullscreenfpupdate"><![CDATA[<link>Actualiza tu Flash Player</link> y <br>usa el <strong>modo de pantalla completa</strong>.]]></item>
  <item name="hint_title_configure_ui"><![CDATA[Configuración de la IU]]></item>
  <item name="hint_title_configure_ui_long"><![CDATA[Configuración de la IU]]></item>
  <item name="hint_subtitle_configure_ui"><![CDATA[Configura la nueva IU en su propia área.]]></item>
  <item name="hint_description_configure_ui"><![CDATA[Encontrarás el <strong>Modo de configuración</strong> en el apartado <strong>Interfaz</strong> del menú <strong>Ajustes</strong>.]]></item>
 </category>
</language>
